musif/__init__.py
musif/__main__.py
musif/cache/__init__.py
musif/cache/cache.py
musif/cache/utils.py
musif/common/__init__.py
musif/common/_constants.py
musif/common/_logs.py
musif/common/_utils.py
musif/common/constants.py
musif/common/didone_utils.py
musif/common/exceptions.py
musif/common/sort.py
musif/common/translate.py
musif/config.py
musif/extract/__init__.py
musif/extract/basic_modules/file_name_generic/__init__.py
musif/extract/basic_modules/file_name_generic/constants.py
musif/extract/basic_modules/file_name_generic/handler.py
musif/extract/basic_modules/scoring/__init__.py
musif/extract/basic_modules/scoring/constants.py
musif/extract/basic_modules/scoring/handler.py
musif/extract/common.py
musif/extract/constants.py
musif/extract/extract.py
musif/extract/features/__init__.py
musif/extract/features/ambitus/__init__.py
musif/extract/features/ambitus/constants.py
musif/extract/features/ambitus/handler.py
musif/extract/features/core/__init__.py
musif/extract/features/core/constants.py
musif/extract/features/core/handler.py
musif/extract/features/density/__init__.py
musif/extract/features/density/constants.py
musif/extract/features/density/handler.py
musif/extract/features/dynamics/__init__.py
musif/extract/features/dynamics/constants.py
musif/extract/features/dynamics/handler.py
musif/extract/features/harmony/__init__.py
musif/extract/features/harmony/constants.py
musif/extract/features/harmony/handler.py
musif/extract/features/harmony/utils.py
musif/extract/features/key/__init__.py
musif/extract/features/key/constants.py
musif/extract/features/key/handler.py
musif/extract/features/lyrics/__init__.py
musif/extract/features/lyrics/constants.py
musif/extract/features/lyrics/handler.py
musif/extract/features/melody/__init__.py
musif/extract/features/melody/constants.py
musif/extract/features/melody/handler.py
musif/extract/features/music21/__init__.py
musif/extract/features/music21/constants.py
musif/extract/features/music21/handler.py
musif-1.2.4.dist-info/WHEEL
musif-1.2.4.dist-info/METADATA
musif-1.2.4.dist-info/RECORD
