Metadata-Version: 2.1
Name: musif
Version: 1.2.4
Summary: Music feature extraction library from the DIDONE project
License: MIT
Author-email: Didone Project <didone@iccmu.es>
Requires-Python: >=3.10
Requires-Dist: deepdiff>=6.2.1
Requires-Dist: joblib>=1.0.0
Requires-Dist: ms3==2.4.2
Requires-Dist: music21>=9.1
Requires-Dist: pandas>=1.3.3
Requires-Dist: pyyaml>=5.4.1
Requires-Dist: roman>=3.3
Requires-Dist: scipy>=1.6.0
Requires-Dist: tqdm>=4.56.0
Requires-Dist: webcolors==1.12
